ansys/meshing/prime/__init__.py
ansys/meshing/prime/_version.py
ansys/meshing/prime/autogen/automesh.py
ansys/meshing/prime/autogen/automeshstructs.py
ansys/meshing/prime/autogen/autoquadmesher.py
ansys/meshing/prime/autogen/autoquadmesherstructs.py
ansys/meshing/prime/autogen/boundaryfittednurbs.py
ansys/meshing/prime/autogen/collapsetool.py
ansys/meshing/prime/autogen/collapsetoolstructs.py
ansys/meshing/prime/autogen/commonstructs.py
ansys/meshing/prime/autogen/commontypes.py
ansys/meshing/prime/autogen/connect.py
ansys/meshing/prime/autogen/connectstructs.py
ansys/meshing/prime/autogen/controldata.py
ansys/meshing/prime/autogen/controlstructs.py
ansys/meshing/prime/autogen/coreobject.py
ansys/meshing/prime/autogen/deletetool.py
ansys/meshing/prime/autogen/deletetoolstructs.py
ansys/meshing/prime/autogen/featureextraction.py
ansys/meshing/prime/autogen/featureextractionstructs.py
ansys/meshing/prime/autogen/fileio.py
ansys/meshing/prime/autogen/fileiostructs.py
ansys/meshing/prime/autogen/hextospline.py
ansys/meshing/prime/autogen/igastructs.py
ansys/meshing/prime/autogen/materialpointmanager.py
ansys/meshing/prime/autogen/materialpointmanagerstructs.py
ansys/meshing/prime/autogen/meshinfo.py
ansys/meshing/prime/autogen/meshinfostructs.py
ansys/meshing/prime/autogen/model.py
ansys/meshing/prime/autogen/modelstructs.py
ansys/meshing/prime/autogen/morpher.py
ansys/meshing/prime/autogen/morpherbcsstructs.py
ansys/meshing/prime/autogen/morpherstructs.py
ansys/meshing/prime/autogen/multizonecontrol.py
ansys/meshing/prime/autogen/part.py
ansys/meshing/prime/autogen/partstructs.py
ansys/meshing/prime/autogen/periodiccontrol.py
ansys/meshing/prime/autogen/periodiccontrolstructs.py
ansys/meshing/prime/autogen/primeconfig.py
ansys/meshing/prime/autogen/prismcontrol.py
ansys/meshing/prime/autogen/prismcontrolstructs.py
ansys/meshing/prime/autogen/quadtospline.py
ansys/meshing/prime/autogen/scaffolder.py
ansys/meshing/prime/autogen/scaffolderstructs.py
ansys_meshing_prime-0.9.5.dist-info/licenses/LICENSE
ansys_meshing_prime-0.9.5.dist-info/WHEEL
ansys_meshing_prime-0.9.5.dist-info/METADATA
ansys_meshing_prime-0.9.5.dist-info/RECORD
