Metadata-Version: 2.4
Name: ansys-meshing-prime
Version: 0.9.5
Summary: PyPrimeMesh is a Python client to Ansys Prime Server, which delivers core Ansys meshing technology.
Author-email: "ANSYS, Inc." <pyansys.core@ansys.com>
Maintainer-email: "ANSYS, Inc." <pyansys.core@ansys.com>
Requires-Python: >=3.10,<4
Classifier: Development Status :: 4 - Beta
Classifier: License :: OSI Approved :: MIT License
Classifier: Operating System :: OS Independent
Classifier: Programming Language :: Python :: 3.10
Classifier: Programming Language :: Python :: 3.11
Classifier: Programming Language :: Python :: 3.12
Classifier: Programming Language :: Python :: 3.13
License-File: LICENSE
Requires-Dist: ansys-api-meshing-prime==0.1.4
Requires-Dist: numpy>=1.14.0
Requires-Dist: appdirs>=1.4.0
Requires-Dist: importlib-metadata>=4.0,<5; python_version<='3.8'
Requires-Dist: numpy<2.3
Requires-Dist: ansys-tools-visualization-interface>=0.4.7,<=0.11.0 ; extra == "all"
Requires-Dist: pyvista[trame]<=0.45.3 ; extra == "all"
Requires-Dist: ansys-sphinx-theme[autoapi]==1.6.4 ; extra == "doc"
Requires-Dist: ansys-tools-visualization-interface==0.9.2 ; extra == "doc"
Requires-Dist: jupyter-sphinx==0.5.3 ; extra == "doc"
Requires-Dist: numpydoc==1.8.0 ; extra == "doc"
Requires-Dist: sphinx==8.2.3 ; extra == "doc"
Requires-Dist: sphinx_design==0.6.1 ; extra == "doc"
Requires-Dist: pyvista==0.45.2 ; extra == "doc"
Requires-Dist: sphinx-autodoc-typehints==3.1.0 ; extra == "doc"
Requires-Dist: sphinx-copybutton==0.5.2 ; extra == "doc"
Requires-Dist: sphinx-gallery==0.19.0 ; extra == "doc"
Requires-Dist: sphinx-notfound-page==1.1.0 ; extra == "doc"
Requires-Dist: sphinxemoji==0.3.1 ; extra == "doc"
Requires-Dist: ansys-tools-visualization-interface>=0.4.7,<=0.11.0 ; extra == "graphics"
Requires-Dist: pyvista[trame]<=0.45.3 ; extra == "graphics"
Requires-Dist: ansys-tools-visualization-interface==0.9.2 ; extra == "tests"
Requires-Dist: pytest==8.4.1 ; extra == "tests"
Requires-Dist: pytest-cov==6.2.1 ; extra == "tests"
Requires-Dist: pytest-pyvista==0.1.9 ; extra == "tests"
Requires-Dist: pytest-xvfb==3.1.1 ; extra == "tests"
Requires-Dist: pyvista[trame]==0.45.2 ; extra == "tests"
Project-URL: Discussions, https://github.com/ansys/pyprimemesh/discussions
Project-URL: Documentation, https://prime.docs.pyansys.com
Project-URL: Issues, https://github.com/ansys/pyprimemesh/issues
Project-URL: Releases, https://github.com/ansys/pyprimemesh/releases
Project-URL: Source, https://github.com/ansys/pyprimemesh
Provides-Extra: all
Provides-Extra: doc
Provides-Extra: graphics
Provides-Extra: tests
